Metadata-Version: 1.1
Name: gphoto2-cffi
Version: 0.4
Summary: libgphoto2 bindings with an interface that strives to be idiomatic
Home-page: http://github.com/jbaiter/gphoto2-cffi.git
Author: Johannes Baiter
Author-email: johannes.baiter@gmail.com
License: LGPLv3
Platform: UNKNOWN
Classifier: Programming Language :: Python :: 2
Classifier: Programming Language :: Python :: 2.7
Classifier: Programming Language :: Python :: 3
Classifier: Programming Language :: Python :: 3.4
Classifier: Programming Language :: Python :: 3.5
